iconarray/__init__.py
iconarray/backend/__init__.py
iconarray/backend/grid.py
iconarray/core/__init__.py
iconarray/core/crop.py
iconarray/core/interpolate.py
iconarray/core/latlonhash.py
iconarray/core/utilities.py
iconarray/plot/__init__.py
iconarray/plot/config.py
iconarray/plot/formatoptions/__init__.py
iconarray/plot/formatoptions/borders.py
iconarray/plot/formatoptions/customtext.py
iconarray/plot/formatoptions/lakes.py
iconarray/plot/formatoptions/meanmaxwind.py
iconarray/plot/formatoptions/rivers.py
iconarray/plot/formatoptions/standardtitle.py
iconarray/utils/__init__.py
iconarray/utils/get_data.py
iconarray-0.3.2.dist-info/LICENSE
iconarray-0.3.2.dist-info/METADATA
iconarray-0.3.2.dist-info/WHEEL
iconarray-0.3.2.dist-info/top_level.txt
iconarray-0.3.2.dist-info/RECORD
