Metadata-Version: 2.1
Name: iconarray
Version: 0.3.2
Summary: A package of modules for processing and plotting ICON data.
Home-page: https://github.com/C2SM/iconarray
Author: MeteoSwiss, C2SM
Author-email: victoria.cherkas@meteoswiss.ch, annika.lauber@c2sm.ethz.ch
Requires-Python: >=3.7, <4
License-File: LICENSE
Requires-Dist: cfgrib (>=0.9.9.1)
Requires-Dist: xarray (>=0.15)
Requires-Dist: psyplot
Requires-Dist: psy-reg
Requires-Dist: psy-simple
Requires-Dist: psy-maps
Requires-Dist: numpy
Requires-Dist: six
Requires-Dist: cartopy
Provides-Extra: tests
Requires-Dist: flake8 ; extra == 'tests'
Requires-Dist: pytest ; extra == 'tests'
